waterfall_ax/__init__.py
waterfall_ax/waterfall_ax.py
waterfall_ax-1.0.0.dist-info/LICENSE
waterfall_ax-1.0.0.dist-info/METADATA
waterfall_ax-1.0.0.dist-info/WHEEL
waterfall_ax-1.0.0.dist-info/top_level.txt
waterfall_ax-1.0.0.dist-info/RECORD
