Metadata-Version: 2.1
Name: waterfall-ax
Version: 1.0.0
Summary: Create waterfall charts.
Home-page: https://github.com/microsoft/waterfall_ax
Author: Yaran Fan
Author-email: yarfan.fan@gmail.com
License: UNKNOWN
Platform: UNKNOWN
Classifier: Programming Language :: Python :: 3
Classifier: License :: OSI Approved :: MIT License
Classifier: Operating System :: OS Independent
Requires-Python: >=3.6
